podm/__init__.py
podm/aliases.py
podm/handlers.py
podm/jsonobject.py
podm/meta.py
podm/processor.py
podm/properties.py
podm/schema.py
podm/validation.py
podm/util/__init__.py
podm/util/mongo/__init__.py
podm/util/mongo/aggregate.py
podm/util/mongo/expressions.py
podm/util/mongo/query.py
test/__init__.py
test/common.py
test/test_basic.py
test/test_defaults.py
test/test_handlers.py
test/test_processor.py
test/test_query_helper.py
test/test_schema.py
test/test_serialization.py
test/test_validation.py
podm-0.0.19.dist-info/LICENSE
podm-0.0.19.dist-info/METADATA
podm-0.0.19.dist-info/WHEEL
podm-0.0.19.dist-info/top_level.txt
podm-0.0.19.dist-info/RECORD
