Metadata-Version: 2.1
Name: podm
Version: 0.0.19
Summary: A Object-JSON Document mapper
Home-page: https://github.com/Carlos-Descalzi/podm
Author: Carlos Descalzi
Author-email: carlos.descalzi@gmail.com
License: UNKNOWN
Platform: UNKNOWN
Classifier: Programming Language :: Python :: 3
Classifier: License :: OSI Approved :: GNU Library or Lesser General Public License (LGPL)
Classifier: Operating System :: OS Independent
Requires-Python: >=3.6
